odoo/addons/business_requirement_sale/README.rst
odoo/addons/business_requirement_sale/__init__.py
odoo/addons/business_requirement_sale/__manifest__.py
odoo/addons/business_requirement_sale/i18n/es.po
odoo/addons/business_requirement_sale/models/__init__.py
odoo/addons/business_requirement_sale/models/business_requirement.py
odoo/addons/business_requirement_sale/models/business_requirement_deliverable.py
odoo/addons/business_requirement_sale/models/sale_layout_category.py
odoo/addons/business_requirement_sale/models/sale_order.py
odoo/addons/business_requirement_sale/readme/CONTRIBUTORS.rst
odoo/addons/business_requirement_sale/readme/DESCRIPTION.rst
odoo/addons/business_requirement_sale/readme/ROADMAP.rst
odoo/addons/business_requirement_sale/readme/USAGE.rst
odoo/addons/business_requirement_sale/static/description/icon.png
odoo/addons/business_requirement_sale/static/description/index.html
odoo/addons/business_requirement_sale/tests/__init__.py
odoo/addons/business_requirement_sale/tests/test_business_requirement_sale.py
odoo/addons/business_requirement_sale/views/business_requirement_views.xml
odoo/addons/business_requirement_sale/views/sale_order_views.xml
odoo/addons/business_requirement_sale/wizard/__init__.py
odoo/addons/business_requirement_sale/wizard/business_requirement_create_sale.py
odoo/addons/business_requirement_sale/wizard/business_requirement_create_sale_views.xml
odoo11_addon_business_requirement_sale-11.0.1.1.0.dist-info/METADATA
odoo11_addon_business_requirement_sale-11.0.1.1.0.dist-info/RECORD
odoo11_addon_business_requirement_sale-11.0.1.1.0.dist-info/WHEEL
odoo11_addon_business_requirement_sale-11.0.1.1.0.dist-info/top_level.txt
